MANIFEST.in
README.rst
setup.py
doc/file_list.png
doc/settings.png
yidashcam/__init__.py
yidashcam/__main__.py
yidashcam/config.py
yidashcam/webapp.py
yidashcam.egg-info/PKG-INFO
yidashcam.egg-info/SOURCES.txt
yidashcam.egg-info/dependency_links.txt
yidashcam.egg-info/not-zip-safe
yidashcam.egg-info/requires.txt
yidashcam.egg-info/top_level.txt
yidashcam/templates/base.html
yidashcam/templates/error.html
yidashcam/templates/file_list.html
yidashcam/templates/settings.html