Metadata-Version: 1.1
Name: yidashcam
Version: 0.7
Summary: An unofficial python library for interfacing with the Xiaomi YI Dash Cam.
Home-page: https://github.com/kwirk/yidashcam
Author: Steven Hiscocks
Author-email: steven@hiscocks.me.uk
License: MIT
Keywords: xiaomi yi dashcam
Platform: UNKNOWN
Classifier: Development Status :: 4 - Beta
Classifier: License :: OSI Approved :: MIT License
Classifier: Programming Language :: Python :: 3
Classifier: Programming Language :: Python :: 3.4
Classifier: Programming Language :: Python :: 3.5
